astspy.py
astspy-0.0.3.dist-info/LICENSE
astspy-0.0.3.dist-info/METADATA
astspy-0.0.3.dist-info/WHEEL
astspy-0.0.3.dist-info/entry_points.txt
astspy-0.0.3.dist-info/top_level.txt
astspy-0.0.3.dist-info/RECORD
