Metadata-Version: 2.1
Name: astspy
Version: 0.0.3
Summary: Abstract Syntax Tree SPY
Home-page: https://github.com/Ragnarok540/astspy
Author: Edgar Nova
Author-email: ragnarok540@gmail.com
License: UNKNOWN
Keywords: ast,spy,static code analysis,abstract syntax tree
Platform: UNKNOWN
Classifier: Programming Language :: Python :: 3
Classifier: Programming Language :: Python :: 2.7
Classifier: License :: OSI Approved :: MIT License
Classifier: Operating System :: OS Independent
